Workbook

Sheet Simulador
B1: SIMULADOR DE FUNDOS IMOBILIÁRIOS
B4: Preencha as células amarelas (texto azul). As células cinzas são calculadas e não devem ser editadas.
B6: Configurações
B7: Salário mensal (R$) | C7: 5000
B8: Rendimento mensal da carteira | C8: 0.008
B9: % do salário para aportar | C9: 0.3
B10: Aporte sugerido (R$) | C10: =salario*pct_sugestao -> 1500
B11: Perfil de investidor | C11: Moderado
B13: Simulação: as cinco perguntas
B14: 1. Quanto investir por mês (R$) | C14: 1000
B15: 2. Por quantos anos | C15: 10
B16: 3. Taxa de rendimento mensal | C16: =taxa_mensal -> 0.008
B17: 4. Patrimônio acumulado (R$) | C17: =FV(taxa_mensal,anos*12,-aporte) -> 200217.47
B18: 5. Dividendos por mês (R$) | C18: =patrimonio*taxa_mensal -> 1601.7398
B19: Total aportado do próprio bolso (R$) | C19: =aporte*anos*12 -> 120000
B21: Cenários de 2 a 30 anos
B22: Prazo (anos) | C22: Patrimônio com aporte informado | D22: Dividendos/mês (informado) | E22: Patrimônio com aporte sugerido | F22: Dividendos/mês (sugerido)
B23: 2 | C23: =FV(taxa_mensal,$B23*12,-aporte) -> 26343.155 | D23: =C23*taxa_mensal -> 210.74524 | E23: =FV(taxa_mensal,$B23*12,-aporte_sugerido) -> 39514.733 | F23: =E23*taxa_mensal -> 316.11786
B24: 5 | C24: =FV(taxa_mensal,$B24*12,-aporte) -> 76623.867 | D24: =C24*taxa_mensal -> 612.99093 | E24: =FV(taxa_mensal,$B24*12,-aporte_sugerido) -> 114935.8 | F24: =E24*taxa_mensal -> 919.4864
B25: 10 | C25: =FV(taxa_mensal,$B25*12,-aporte) -> 200217.47 | D25: =C25*taxa_mensal -> 1601.7398 | E25: =FV(taxa_mensal,$B25*12,-aporte_sugerido) -> 300326.2 | F25: =E25*taxa_mensal -> 2402.6096
B26: 20 | C26: =FV(taxa_mensal,$B26*12,-aporte) -> 721131.22 | D26: =C26*taxa_mensal -> 5769.0498 | E26: =FV(taxa_mensal,$B26*12,-aporte_sugerido) -> 1081696.8 | F26: =E26*taxa_mensal -> 8653.5746
B27: 30 | C27: =FV(taxa_mensal,$B27*12,-aporte) -> 2076413.2 | D27: =C27*taxa_mensal -> 16611.306 | E27: =FV(taxa_mensal,$B27*12,-aporte_sugerido) -> 3114619.8 | F27: =E27*taxa_mensal -> 24916.959
B29: Divisão do aporte conforme o perfil
B30: Tipo de fundo | C30: Percentual | D30: Aporte informado (R$) | E30: Aporte sugerido (R$)
B31: =Apoio!J5 -> Logística | C31: =VLOOKUP(perfil&B31,tabela_perfil,4,0) -> 0.2 | D31: =C31*aporte -> 200 | E31: =C31*aporte_sugerido -> 300
B32: =Apoio!J6 -> Lajes Corporativas | C32: =VLOOKUP(perfil&B32,tabela_perfil,4,0) -> 0.15 | D32: =C32*aporte -> 150 | E32: =C32*aporte_sugerido -> 225
B33: =Apoio!J7 -> Shoppings | C33: =VLOOKUP(perfil&B33,tabela_perfil,4,0) -> 0.2 | D33: =C33*aporte -> 200 | E33: =C33*aporte_sugerido -> 300
B34: =Apoio!J8 -> Papel (CRI) | C34: =VLOOKUP(perfil&B34,tabela_perfil,4,0) -> 0.2 | D34: =C34*aporte -> 200 | E34: =C34*aporte_sugerido -> 300
B35: =Apoio!J9 -> Fundo de Fundos | C35: =VLOOKUP(perfil&B35,tabela_perfil,4,0) -> 0.15 | D35: =C35*aporte -> 150 | E35: =C35*aporte_sugerido -> 225
B36: =Apoio!J10 -> Desenvolvimento | C36: =VLOOKUP(perfil&B36,tabela_perfil,4,0) -> 0.1 | D36: =C36*aporte -> 100 | E36: =C36*aporte_sugerido -> 150
B37: Total | C37: =SUM(C31:C36) -> 1 | D37: =SUM(D31:D36) -> 1000 | E37: =SUM(E31:E36) -> 1500
B39: Premissas: salário, rendimento (0,8% ao mês), aporte (R$ 1.000) e perfis são valores de exemplo, não recomendação de investimento.
B40: Dividendos mensais = patrimônio acumulado x taxa mensal (premissa: o fundo distribui o rendimento mensal sobre o patrimônio).
B41: Aportes no fim de cada mês (tipo 0 do VF). Rendimento constante: a planilha não considera impostos, taxas nem variação das cotas.

Sheet Apoio
A1: Apoio: tabela de perfis e tipos de fundo
A3: Percentuais de exemplo (valores didáticos), não são recomendação de investimento. Troque pelos seus, mantendo 100% por perfil.
A4: Chave (perfil+tipo) | B4: Perfil | C4: Tipo de fundo | D4: Percentual | F4: Perfil | G4: Soma | H4: Conferência | J4: Tipos de fundo
A5: =B5&C5 -> ConservadorLogística | B5: Conservador | C5: Logística | D5: 0.25 | F5: Conservador | G5: =SUMIF($B$5:$B$22,F5,$D$5:$D$22) -> 1 | H5: =IF(ROUND(G5,6)=1,"OK","Revisar") -> OK | J5: Logística
A6: =B6&C6 -> ConservadorLajes Corporativas | B6: Conservador | C6: Lajes Corporativas | D6: 0.2 | F6: Moderado | G6: =SUMIF($B$5:$B$22,F6,$D$5:$D$22) -> 1 | H6: =IF(ROUND(G6,6)=1,"OK","Revisar") -> OK | J6: Lajes Corporativas
A7: =B7&C7 -> ConservadorShoppings | B7: Conservador | C7: Shoppings | D7: 0.15 | F7: Arrojado | G7: =SUMIF($B$5:$B$22,F7,$D$5:$D$22) -> 1 | H7: =IF(ROUND(G7,6)=1,"OK","Revisar") -> OK | J7: Shoppings
A8: =B8&C8 -> ConservadorPapel (CRI) | B8: Conservador | C8: Papel (CRI) | D8: 0.25 | J8: Papel (CRI)
A9: =B9&C9 -> ConservadorFundo de Fundos | B9: Conservador | C9: Fundo de Fundos | D9: 0.1 | J9: Fundo de Fundos
A10: =B10&C10 -> ConservadorDesenvolvimento | B10: Conservador | C10: Desenvolvimento | D10: 0.05 | J10: Desenvolvimento
A11: =B11&C11 -> ModeradoLogística | B11: Moderado | C11: Logística | D11: 0.2
A12: =B12&C12 -> ModeradoLajes Corporativas | B12: Moderado | C12: Lajes Corporativas | D12: 0.15
A13: =B13&C13 -> ModeradoShoppings | B13: Moderado | C13: Shoppings | D13: 0.2
A14: =B14&C14 -> ModeradoPapel (CRI) | B14: Moderado | C14: Papel (CRI) | D14: 0.2
A15: =B15&C15 -> ModeradoFundo de Fundos | B15: Moderado | C15: Fundo de Fundos | D15: 0.15
A16: =B16&C16 -> ModeradoDesenvolvimento | B16: Moderado | C16: Desenvolvimento | D16: 0.1
A17: =B17&C17 -> ArrojadoLogística | B17: Arrojado | C17: Logística | D17: 0.15
A18: =B18&C18 -> ArrojadoLajes Corporativas | B18: Arrojado | C18: Lajes Corporativas | D18: 0.1
A19: =B19&C19 -> ArrojadoShoppings | B19: Arrojado | C19: Shoppings | D19: 0.2
A20: =B20&C20 -> ArrojadoPapel (CRI) | B20: Arrojado | C20: Papel (CRI) | D20: 0.15
A21: =B21&C21 -> ArrojadoFundo de Fundos | B21: Arrojado | C21: Fundo de Fundos | D21: 0.15
A22: =B22&C22 -> ArrojadoDesenvolvimento | B22: Arrojado | C22: Desenvolvimento | D22: 0.25
A24: Legenda: texto azul = valor editável; fundo cinza = fórmula (não editar). A chave composta (coluna A) fica à esquerda porque o PROCV só busca na primeira coluna da tabela.
